{
    "sourceFile": "src/app/pages/candidate/profile/popupCVMangagement/popup-cv-management.component.ts",
    "activeCommit": 0,
    "commits": [
        {
            "activePatchIndex": 5,
            "patches": [
                {
                    "date": 1755071720158,
                    "content": "Index: \n===================================================================\n--- \n+++ \n"
                },
                {
                    "date": 1755074023191,
                    "content": "Index: \n===================================================================\n--- \n+++ \n@@ -6,8 +6,9 @@\n import { UtilsService } from 'src/app/helper/service/utils.service';\r\n import { CommonService } from 'src/app/service/common.service';\r\n import { ExportService } from 'src/app/service/export.service';\r\n import { environment } from 'src/environments/environment';\r\n+import { LocalStorageService } from 'src/app/core/auth/local-storage.service';\r\n @Component({\r\n   selector: 'app-popup-cv-management',\r\n   templateUrl: './popup-cv-management.component.html',\r\n   styleUrls: ['./popup-cv-management.component.scss']\r\n@@ -23,9 +24,10 @@\n \r\n   constructor(\r\n     private commonService: CommonService,\r\n     private utilsService: UtilsService,\r\n-\t\tprivate exportService:ExportService\r\n+\t\tprivate exportService:ExportService,\r\n+     private localStorageService: LocalStorageService\r\n   ) { }\r\n \r\n   ngOnInit() {\r\n     this.init();\r\n@@ -92,35 +94,50 @@\n     this.checkedItems = items;\r\n   }\r\n \r\n   delete() {\r\n-  if (!this.checkedItems || this.checkedItems.length === 0) {\r\n-    return;\r\n-  }\r\n+    if (!this.checkedItems || this.checkedItems.length === 0) {\r\n+      alert('Vui lòng chọn ít nhất một CV để xóa.');\r\n+      return;\r\n+    }\r\n \r\n-  if (!confirm('Bạn có chắc muốn xóa các CV đã chọn?')) {\r\n-    return;\r\n-  }\r\n+    const userId = this.utilsService.getItem(ConstantsApp.user).id;\r\n+    if (!userId) {\r\n+      alert('Không tìm thấy thông tin người dùng. Vui lòng đăng nhập lại.');\r\n+      return;\r\n+    }\r\n \r\n-  const ids = this.checkedItems.map((item: any) => item.id);\r\n+    // Kiểm tra quyền sở hữu\r\n+    const invalidItems = this.checkedItems.filter((item: any) => item.userId !== userId);\r\n+    if (invalidItems.length > 0) {\r\n+      alert('Bạn chỉ có thể xóa các CV của chính mình.');\r\n+      return;\r\n+    }\r\n \r\n-  const apiUrl = environment.API_URI + ApiNameConstants.BS_DELETE_CV; // cần định nghĩa trong ApiNameConstants\r\n+    if (!confirm('Bạn có chắc muốn xóa các CV đã chọn?')) {\r\n+      return;\r\n+    }\r\n \r\n-  this.commonService\r\n-    .postDatas({ ids }, apiUrl, 'delete', 'Delete candidate CVs')\r\n-    .subscribe({\r\n-      next: (res: any) => {\r\n-        alert('Xóa thành công');\r\n-        this.getData();\r\n-      },\r\n-      error: (err) => {\r\n-        console.error('Lỗi khi xóa CV:', err);\r\n-        alert('Xóa thất bại');\r\n-      }\r\n-    });\r\n-}\r\n+    const cvIds = this.checkedItems.map((item: any) => item.id); // Lấy danh sách ID của CV (freelancer ID)\r\n+    const apiUrl = environment.API_URI + ApiNameConstants.BS_DELETE_CV;\r\n \r\n+    this.commonService\r\n+      .postDatas({ userId, cvIds }, apiUrl, 'delete', 'Delete candidate CVs')\r\n+      .subscribe({\r\n+        next: (res: any) => {\r\n+          alert('Xóa thành công');\r\n+          this.checkedItems = [];\r\n+          this.getData();\r\n+        },\r\n+        error: (err) => {\r\n+          console.error('Lỗi khi xóa CV:', err);\r\n+          const errorMessage = err.error?.error || 'Xóa thất bại';\r\n+          alert(errorMessage);\r\n+        }\r\n+      });\r\n+  }\r\n \r\n+\r\n   exportFile() {\r\n     if (this.checkedItems && this.checkedItems.length > 0) {\r\n       //   call API\r\n \t\t\tthis.exportService.exportExcel(this.checkedItems,\"candidatePosts\")\r\n"
                },
                {
                    "date": 1755074072790,
                    "content": "Index: \n===================================================================\n--- \n+++ \n@@ -105,14 +105,9 @@\n       alert('Không tìm thấy thông tin người dùng. Vui lòng đăng nhập lại.');\r\n       return;\r\n     }\r\n \r\n-    // Kiểm tra quyền sở hữu\r\n-    const invalidItems = this.checkedItems.filter((item: any) => item.userId !== userId);\r\n-    if (invalidItems.length > 0) {\r\n-      alert('Bạn chỉ có thể xóa các CV của chính mình.');\r\n-      return;\r\n-    }\r\n+    \r\n \r\n     if (!confirm('Bạn có chắc muốn xóa các CV đã chọn?')) {\r\n       return;\r\n     }\r\n"
                },
                {
                    "date": 1755075405195,
                    "content": "Index: \n===================================================================\n--- \n+++ \n@@ -24,33 +24,33 @@\n \r\n   constructor(\r\n     private commonService: CommonService,\r\n     private utilsService: UtilsService,\r\n-\t\tprivate exportService:ExportService,\r\n-     private localStorageService: LocalStorageService\r\n+    private exportService: ExportService,\r\n+    private localStorageService: LocalStorageService\r\n   ) { }\r\n \r\n   ngOnInit() {\r\n     this.init();\r\n   }\r\n   init() {\r\n     this.displayedColumns = [\r\n       {\r\n-\t\t\t\tname: Constants.CV,\r\n-\t\t\t\tkey: ConstantsApp.cv,\r\n-\t\t\t\tisAsc: true\r\n-\t\t\t},\r\n-\t\t\t{\r\n-\t\t\t\tname: Constants.jobLbl,\r\n-\t\t\t\tkey: ConstantsApp.jdName,\r\n-\t\t\t\tisAsc: true\r\n-\t\t\t},\r\n-\t\t\t{\r\n-\t\t\t\tname: Constants.creationDateLbl,\r\n-\t\t\t\tkey: ConstantsApp.creationDate,\r\n-\t\t\t\tisAsc: true\r\n-\t\t\t}\r\n-\t\t]\r\n+        name: Constants.CV,\r\n+        key: ConstantsApp.cv,\r\n+        isAsc: true\r\n+      },\r\n+      {\r\n+        name: Constants.jobLbl,\r\n+        key: ConstantsApp.jdName,\r\n+        isAsc: true\r\n+      },\r\n+      {\r\n+        name: Constants.creationDateLbl,\r\n+        key: ConstantsApp.creationDate,\r\n+        isAsc: true\r\n+      }\r\n+    ]\r\n     this.getData();\r\n   }\r\n   closePage() {\r\n     this.closeCVManagePage.emit(false);\r\n@@ -66,9 +66,9 @@\n     this.commonService\r\n       .postDatas(paging, apiUrl, functionName, messageLog)\r\n       .subscribe((res: any) => {\r\n         this.dataOrg = res;\r\n-        if(this.dataOrg.data) {\r\n+        if (this.dataOrg.data) {\r\n           this.dataOrg.data = this.dataOrg.data.filter((item: any) => item.cv)\r\n         }\r\n         let temp: any[] = [];\r\n         let dataTable = this.dataOrg.data;\r\n@@ -105,15 +105,22 @@\n       alert('Không tìm thấy thông tin người dùng. Vui lòng đăng nhập lại.');\r\n       return;\r\n     }\r\n \r\n-    \r\n+    // Lọc bỏ các item không có id hoặc id là null\r\n+    const cvIds = this.checkedItems\r\n+      .map((item: any) => item.id)\r\n+      .filter((id: any) => id != null); // Loại bỏ null và undefined\r\n \r\n+    if (cvIds.length === 0) {\r\n+      alert('Không có CV hợp lệ được chọn để xóa.');\r\n+      return;\r\n+    }\r\n+\r\n     if (!confirm('Bạn có chắc muốn xóa các CV đã chọn?')) {\r\n       return;\r\n     }\r\n \r\n-    const cvIds = this.checkedItems.map((item: any) => item.id); // Lấy danh sách ID của CV (freelancer ID)\r\n     const apiUrl = environment.API_URI + ApiNameConstants.BS_DELETE_CV;\r\n \r\n     this.commonService\r\n       .postDatas({ userId, cvIds }, apiUrl, 'delete', 'Delete candidate CVs')\r\n@@ -134,8 +141,8 @@\n \r\n   exportFile() {\r\n     if (this.checkedItems && this.checkedItems.length > 0) {\r\n       //   call API\r\n-\t\t\tthis.exportService.exportExcel(this.checkedItems,\"candidatePosts\")\r\n+      this.exportService.exportExcel(this.checkedItems, \"candidatePosts\")\r\n     }\r\n   }\r\n }\r\n"
                },
                {
                    "date": 1755076184599,
                    "content": "Index: \n===================================================================\n--- \n+++ \n@@ -0,0 +1,155 @@\n+import { Component, EventEmitter, OnInit, Output } from '@angular/core';\r\n+import * as $ from 'jquery';\r\n+import { ApiNameConstants } from 'src/app/constant/ApiNameConstants';\r\n+import { Constants } from 'src/app/constant/Constants';\r\n+import { ConstantsApp } from 'src/app/constant/ConstantsApp';\r\n+import { UtilsService } from 'src/app/helper/service/utils.service';\r\n+import { CommonService } from 'src/app/service/common.service';\r\n+import { ExportService } from 'src/app/service/export.service';\r\n+import { environment } from 'src/environments/environment';\r\n+import { LocalStorageService } from 'src/app/core/auth/local-storage.service';\r\n+@Component({\r\n+  selector: 'app-popup-cv-management',\r\n+  templateUrl: './popup-cv-management.component.html',\r\n+  styleUrls: ['./popup-cv-management.component.scss']\r\n+})\r\n+export class PopupCVMangagementComponent implements OnInit {\r\n+  @Output() closeCVManagePage = new EventEmitter();\r\n+  displayedColumns: any = [];\r\n+  dataOrg: any;\r\n+  isShowDetail: any;\r\n+  item: any;\r\n+  checkedItems: any;\r\n+  pageNum: number = 1;\r\n+\r\n+  constructor(\r\n+    private commonService: CommonService,\r\n+    private utilsService: UtilsService,\r\n+    private exportService: ExportService,\r\n+    private localStorageService: LocalStorageService\r\n+  ) { }\r\n+\r\n+  ngOnInit() {\r\n+    this.init();\r\n+  }\r\n+  init() {\r\n+    this.displayedColumns = [\r\n+      {\r\n+        name: Constants.CV,\r\n+        key: ConstantsApp.cv,\r\n+        isAsc: true\r\n+      },\r\n+      {\r\n+        name: Constants.jobLbl,\r\n+        key: ConstantsApp.jdName,\r\n+        isAsc: true\r\n+      },\r\n+      {\r\n+        name: Constants.creationDateLbl,\r\n+        key: ConstantsApp.creationDate,\r\n+        isAsc: true\r\n+      }\r\n+    ]\r\n+    this.getData();\r\n+  }\r\n+  closePage() {\r\n+    this.closeCVManagePage.emit(false);\r\n+  }\r\n+  getData() {\r\n+    let paging = {\r\n+      page: this.pageNum,\r\n+      size: 100\r\n+    }\r\n+    const functionName = 'getData';\r\n+    const messageLog = 'get candidate posts';\r\n+    const apiUrl = environment.API_URI + ApiNameConstants.BS_USER_CANDIDATE_POSTS\r\n+    this.commonService\r\n+      .postDatas(paging, apiUrl, functionName, messageLog)\r\n+      .subscribe((res: any) => {\r\n+        this.dataOrg = res;\r\n+        if (this.dataOrg.data) {\r\n+          this.dataOrg.data = this.dataOrg.data.filter((item: any) => item.cv)\r\n+        }\r\n+        let temp: any[] = [];\r\n+        let dataTable = this.dataOrg.data;\r\n+        console.log(dataTable);\r\n+        dataTable.map((item: any) => {\r\n+          item.creationDate = this.utilsService.formatDate(item.creationDate);\r\n+          temp.push(item);\r\n+        });\r\n+        this.dataOrg.data = temp;\r\n+      });\r\n+  }\r\n+  changePage(currentPage: any) {\r\n+    this.pageNum = currentPage;\r\n+    this.getData();\r\n+  }\r\n+\r\n+  showDetail(item: any) {\r\n+    this.item = item;\r\n+    this.isShowDetail = true;\r\n+  }\r\n+\r\n+  getCheckedItems(items: any) {\r\n+    this.checkedItems = items;\r\n+  }\r\n+\r\n+  delete() {\r\n+    if (!this.checkedItems || this.checkedItems.length === 0) {\r\n+      alert('Vui lòng chọn ít nhất một CV để xóa.');\r\n+      return;\r\n+    }\r\n+\r\n+    const userId = this.utilsService.getItem(ConstantsApp.user).id;\r\n+    if (!userId) {\r\n+      alert('Không tìm thấy thông tin người dùng. Vui lòng đăng nhập lại.');\r\n+      return;\r\n+    }\r\n+\r\n+    // Lấy danh sách tên CV thay vì ID\r\n+    const cvNames = this.checkedItems\r\n+      .map((item: any) => {\r\n+        if (!item.cv) {\r\n+          console.warn('Item missing cv:', JSON.stringify(item, null, 2));\r\n+        }\r\n+        return item.cv;\r\n+      })\r\n+      .filter((cv: any) => cv != null);\r\n+\r\n+    if (cvNames.length === 0) {\r\n+      console.log('Checked items:', JSON.stringify(this.checkedItems, null, 2));\r\n+      alert('Không có CV hợp lệ được chọn để xóa. Các CV được chọn không có tên hợp lệ.');\r\n+      return;\r\n+    }\r\n+\r\n+    if (!confirm('Bạn có chắc muốn xóa các CV đã chọn?')) {\r\n+      return;\r\n+    }\r\n+\r\n+    const apiUrl = environment.API_URI + ApiNameConstants.BS_DELETE_CV;\r\n+\r\n+    // Gửi danh sách cvNames thay vì cvIds\r\n+    this.commonService\r\n+      .postDatas({ userId, cvNames }, apiUrl, 'delete', 'Delete candidate CVs')\r\n+      .subscribe({\r\n+        next: (res: any) => {\r\n+          alert('Xóa thành công');\r\n+          this.checkedItems = [];\r\n+          this.getData();\r\n+        },\r\n+        error: (err) => {\r\n+          console.error('Lỗi khi xóa CV:', err);\r\n+          const errorMessage = err.error?.error || 'Xóa thất bại';\r\n+          alert(errorMessage);\r\n+        }\r\n+      });\r\n+  }\r\n+\r\n+\r\n+  exportFile() {\r\n+    if (this.checkedItems && this.checkedItems.length > 0) {\r\n+      //   call API\r\n+      this.exportService.exportExcel(this.checkedItems, \"candidatePosts\")\r\n+    }\r\n+  }\r\n+}\r\n"
                },
                {
                    "date": 1757393900414,
                    "content": "Index: \n===================================================================\n--- \n+++ \n@@ -99,9 +99,9 @@\n       alert('Vui lòng chọn ít nhất một CV để xóa.');\r\n       return;\r\n     }\r\n \r\n-    const userId = this.utilsService.getItem(ConstantsApp.user).id;\r\n+    const userId = JSON.parse(this.utilsService.getItem(ConstantsApp.user)).id;\r\n     if (!userId) {\r\n       alert('Không tìm thấy thông tin người dùng. Vui lòng đăng nhập lại.');\r\n       return;\r\n     }\r\n@@ -152,152 +152,4 @@\n       this.exportService.exportExcel(this.checkedItems, \"candidatePosts\")\r\n     }\r\n   }\r\n }\r\n-import { Component, EventEmitter, OnInit, Output } from '@angular/core';\r\n-import * as $ from 'jquery';\r\n-import { ApiNameConstants } from 'src/app/constant/ApiNameConstants';\r\n-import { Constants } from 'src/app/constant/Constants';\r\n-import { ConstantsApp } from 'src/app/constant/ConstantsApp';\r\n-import { UtilsService } from 'src/app/helper/service/utils.service';\r\n-import { CommonService } from 'src/app/service/common.service';\r\n-import { ExportService } from 'src/app/service/export.service';\r\n-import { environment } from 'src/environments/environment';\r\n-import { LocalStorageService } from 'src/app/core/auth/local-storage.service';\r\n-@Component({\r\n-  selector: 'app-popup-cv-management',\r\n-  templateUrl: './popup-cv-management.component.html',\r\n-  styleUrls: ['./popup-cv-management.component.scss']\r\n-})\r\n-export class PopupCVMangagementComponent implements OnInit {\r\n-  @Output() closeCVManagePage = new EventEmitter();\r\n-  displayedColumns: any = [];\r\n-  dataOrg: any;\r\n-  isShowDetail: any;\r\n-  item: any;\r\n-  checkedItems: any;\r\n-  pageNum: number = 1;\r\n-\r\n-  constructor(\r\n-    private commonService: CommonService,\r\n-    private utilsService: UtilsService,\r\n-    private exportService: ExportService,\r\n-    private localStorageService: LocalStorageService\r\n-  ) { }\r\n-\r\n-  ngOnInit() {\r\n-    this.init();\r\n-  }\r\n-  init() {\r\n-    this.displayedColumns = [\r\n-      {\r\n-        name: Constants.CV,\r\n-        key: ConstantsApp.cv,\r\n-        isAsc: true\r\n-      },\r\n-      {\r\n-        name: Constants.jobLbl,\r\n-        key: ConstantsApp.jdName,\r\n-        isAsc: true\r\n-      },\r\n-      {\r\n-        name: Constants.creationDateLbl,\r\n-        key: ConstantsApp.creationDate,\r\n-        isAsc: true\r\n-      }\r\n-    ]\r\n-    this.getData();\r\n-  }\r\n-  closePage() {\r\n-    this.closeCVManagePage.emit(false);\r\n-  }\r\n-  getData() {\r\n-    let paging = {\r\n-      page: this.pageNum,\r\n-      size: 100\r\n-    }\r\n-    const functionName = 'getData';\r\n-    const messageLog = 'get candidate posts';\r\n-    const apiUrl = environment.API_URI + ApiNameConstants.BS_USER_CANDIDATE_POSTS\r\n-    this.commonService\r\n-      .postDatas(paging, apiUrl, functionName, messageLog)\r\n-      .subscribe((res: any) => {\r\n-        this.dataOrg = res;\r\n-        if (this.dataOrg.data) {\r\n-          this.dataOrg.data = this.dataOrg.data.filter((item: any) => item.cv)\r\n-        }\r\n-        let temp: any[] = [];\r\n-        let dataTable = this.dataOrg.data;\r\n-        console.log(dataTable);\r\n-        dataTable.map((item: any) => {\r\n-          item.creationDate = this.utilsService.formatDate(item.creationDate);\r\n-          temp.push(item);\r\n-        });\r\n-        this.dataOrg.data = temp;\r\n-      });\r\n-  }\r\n-  changePage(currentPage: any) {\r\n-    this.pageNum = currentPage;\r\n-    this.getData();\r\n-  }\r\n-\r\n-  showDetail(item: any) {\r\n-    this.item = item;\r\n-    this.isShowDetail = true;\r\n-  }\r\n-\r\n-  getCheckedItems(items: any) {\r\n-    this.checkedItems = items;\r\n-  }\r\n-\r\n-  delete() {\r\n-    if (!this.checkedItems || this.checkedItems.length === 0) {\r\n-      alert('Vui lòng chọn ít nhất một CV để xóa.');\r\n-      return;\r\n-    }\r\n-\r\n-    const userId = this.utilsService.getItem(ConstantsApp.user).id;\r\n-    if (!userId) {\r\n-      alert('Không tìm thấy thông tin người dùng. Vui lòng đăng nhập lại.');\r\n-      return;\r\n-    }\r\n-\r\n-    // Lọc bỏ các item không có id hoặc id là null\r\n-    const cvIds = this.checkedItems\r\n-      .map((item: any) => item.id)\r\n-      .filter((id: any) => id != null); // Loại bỏ null và undefined\r\n-\r\n-    if (cvIds.length === 0) {\r\n-      alert('Không có CV hợp lệ được chọn để xóa.');\r\n-      return;\r\n-    }\r\n-\r\n-    if (!confirm('Bạn có chắc muốn xóa các CV đã chọn?')) {\r\n-      return;\r\n-    }\r\n-\r\n-    const apiUrl = environment.API_URI + ApiNameConstants.BS_DELETE_CV;\r\n-\r\n-    this.commonService\r\n-      .postDatas({ userId, cvIds }, apiUrl, 'delete', 'Delete candidate CVs')\r\n-      .subscribe({\r\n-        next: (res: any) => {\r\n-          alert('Xóa thành công');\r\n-          this.checkedItems = [];\r\n-          this.getData();\r\n-        },\r\n-        error: (err) => {\r\n-          console.error('Lỗi khi xóa CV:', err);\r\n-          const errorMessage = err.error?.error || 'Xóa thất bại';\r\n-          alert(errorMessage);\r\n-        }\r\n-      });\r\n-  }\r\n-\r\n-\r\n-  exportFile() {\r\n-    if (this.checkedItems && this.checkedItems.length > 0) {\r\n-      //   call API\r\n-      this.exportService.exportExcel(this.checkedItems, \"candidatePosts\")\r\n-    }\r\n-  }\r\n-}\r\n"
                }
            ],
            "date": 1755071720158,
            "name": "Commit-0",
            "content": "import { Component, EventEmitter, OnInit, Output } from '@angular/core';\r\nimport * as $ from 'jquery';\r\nimport { ApiNameConstants } from 'src/app/constant/ApiNameConstants';\r\nimport { Constants } from 'src/app/constant/Constants';\r\nimport { ConstantsApp } from 'src/app/constant/ConstantsApp';\r\nimport { UtilsService } from 'src/app/helper/service/utils.service';\r\nimport { CommonService } from 'src/app/service/common.service';\r\nimport { ExportService } from 'src/app/service/export.service';\r\nimport { environment } from 'src/environments/environment';\r\n@Component({\r\n  selector: 'app-popup-cv-management',\r\n  templateUrl: './popup-cv-management.component.html',\r\n  styleUrls: ['./popup-cv-management.component.scss']\r\n})\r\nexport class PopupCVMangagementComponent implements OnInit {\r\n  @Output() closeCVManagePage = new EventEmitter();\r\n  displayedColumns: any = [];\r\n  dataOrg: any;\r\n  isShowDetail: any;\r\n  item: any;\r\n  checkedItems: any;\r\n  pageNum: number = 1;\r\n\r\n  constructor(\r\n    private commonService: CommonService,\r\n    private utilsService: UtilsService,\r\n\t\tprivate exportService:ExportService\r\n  ) { }\r\n\r\n  ngOnInit() {\r\n    this.init();\r\n  }\r\n  init() {\r\n    this.displayedColumns = [\r\n      {\r\n\t\t\t\tname: Constants.CV,\r\n\t\t\t\tkey: ConstantsApp.cv,\r\n\t\t\t\tisAsc: true\r\n\t\t\t},\r\n\t\t\t{\r\n\t\t\t\tname: Constants.jobLbl,\r\n\t\t\t\tkey: ConstantsApp.jdName,\r\n\t\t\t\tisAsc: true\r\n\t\t\t},\r\n\t\t\t{\r\n\t\t\t\tname: Constants.creationDateLbl,\r\n\t\t\t\tkey: ConstantsApp.creationDate,\r\n\t\t\t\tisAsc: true\r\n\t\t\t}\r\n\t\t]\r\n    this.getData();\r\n  }\r\n  closePage() {\r\n    this.closeCVManagePage.emit(false);\r\n  }\r\n  getData() {\r\n    let paging = {\r\n      page: this.pageNum,\r\n      size: 100\r\n    }\r\n    const functionName = 'getData';\r\n    const messageLog = 'get candidate posts';\r\n    const apiUrl = environment.API_URI + ApiNameConstants.BS_USER_CANDIDATE_POSTS\r\n    this.commonService\r\n      .postDatas(paging, apiUrl, functionName, messageLog)\r\n      .subscribe((res: any) => {\r\n        this.dataOrg = res;\r\n        if(this.dataOrg.data) {\r\n          this.dataOrg.data = this.dataOrg.data.filter((item: any) => item.cv)\r\n        }\r\n        let temp: any[] = [];\r\n        let dataTable = this.dataOrg.data;\r\n        console.log(dataTable);\r\n        dataTable.map((item: any) => {\r\n          item.creationDate = this.utilsService.formatDate(item.creationDate);\r\n          temp.push(item);\r\n        });\r\n        this.dataOrg.data = temp;\r\n      });\r\n  }\r\n  changePage(currentPage: any) {\r\n    this.pageNum = currentPage;\r\n    this.getData();\r\n  }\r\n\r\n  showDetail(item: any) {\r\n    this.item = item;\r\n    this.isShowDetail = true;\r\n  }\r\n\r\n  getCheckedItems(items: any) {\r\n    this.checkedItems = items;\r\n  }\r\n\r\n  delete() {\r\n  if (!this.checkedItems || this.checkedItems.length === 0) {\r\n    return;\r\n  }\r\n\r\n  if (!confirm('Bạn có chắc muốn xóa các CV đã chọn?')) {\r\n    return;\r\n  }\r\n\r\n  const ids = this.checkedItems.map((item: any) => item.id);\r\n\r\n  const apiUrl = environment.API_URI + ApiNameConstants.BS_DELETE_CV; // cần định nghĩa trong ApiNameConstants\r\n\r\n  this.commonService\r\n    .postDatas({ ids }, apiUrl, 'delete', 'Delete candidate CVs')\r\n    .subscribe({\r\n      next: (res: any) => {\r\n        alert('Xóa thành công');\r\n        this.getData();\r\n      },\r\n      error: (err) => {\r\n        console.error('Lỗi khi xóa CV:', err);\r\n        alert('Xóa thất bại');\r\n      }\r\n    });\r\n}\r\n\r\n\r\n  exportFile() {\r\n    if (this.checkedItems && this.checkedItems.length > 0) {\r\n      //   call API\r\n\t\t\tthis.exportService.exportExcel(this.checkedItems,\"candidatePosts\")\r\n    }\r\n  }\r\n}\r\n"
        }
    ]
}